{
  "Guest" : {
    "denied" : {},
    "Index" : ["*"],
    "Category" : ["view"],
    "Thread" : ["view"],
    "User" : ["login", "registration"],
    "Recovery" : ["*"],
    "Restricted" : ["*"],
    "Stats" : ["*"],
    "Error" : ["*"]
  },
  "User" : {
    "denied" : {},
    "Index" : ["*"],
    "Category" : ["*"],
    "Thread" : ["*"],
    "User" : ["logout", "profile", "mail", "message", "inbox", "reputation", "rate"],
    "Action" : ["report"],
    "Stats" : ["*"],
    "Search" : ["*"],
    "Error" : ["*"]
  },
  "Moderator" : {
    "denied" : {},
    "Index" : ["*"],
    "Category" : ["*"],
    "Thread" : ["*"],
    "User" : ["logout", "profile", "mail", "message", "inbox", "reputation", "rate"],
    "Action" : ["remove", "report"],
    "Stats" : ["*"],
    "Search" : ["*"],
    "Error" : ["*"]
  },
  "Staff" : {
    "denied" : {},
    "Index" : ["*"],
    "Category" : ["*"],
    "Thread" : ["*"],
    "User" : ["logout", "profile", "mail", "message", "inbox", "reputation", "rate"],
    "Action" : ["remove", "report", "close", "delete"],
    "Stats" : ["*"],
    "Search" : ["*"],
    "Error" : ["*"]
  },
  "Admin" : {
    "denied" : {},
    "Index" : ["*"],
    "Category" : ["*"],
    "Thread" : ["*"],
    "User" : ["logout", "profile", "mail", "message", "inbox", "reputation", "rate"],
    "Action" : ["*"],
    "Stats" : ["*"],
    "Search" : ["*"],
    "Error" : ["*"]
  }
}